paddlerec/__init__.py
paddlerec/run.py
paddlerec/setup.py
paddlerec/core/__init__.py
paddlerec/core/factory.py
paddlerec/core/layer.py
paddlerec/core/metric.py
paddlerec/core/model.py
paddlerec/core/reader.py
paddlerec/core/trainer.py
paddlerec/core/engine/__init__.py
paddlerec/core/engine/cluster_utils.py
paddlerec/core/engine/engine.py
paddlerec/core/engine/local_cluster.py
paddlerec/core/engine/local_mpi.py
paddlerec/core/engine/cluster/__init__.py
paddlerec/core/engine/cluster/cluster.py
paddlerec/core/engine/cluster/cloud/__init__.py
paddlerec/core/engine/cluster/cloud/before_hook_cpu.sh.template
paddlerec/core/engine/cluster/cloud/before_hook_gpu.sh.template
paddlerec/core/engine/cluster/cloud/cluster.sh
paddlerec/core/engine/cluster/cloud/end_hook.sh.template
paddlerec/core/engine/cluster/cloud/k8s_config.ini.template
paddlerec/core/engine/cluster/cloud/k8s_cpu_job.sh.template
paddlerec/core/engine/cluster/cloud/k8s_job.sh.template
paddlerec/core/engine/cluster/cloud/mpi_config.ini.template
paddlerec/core/engine/cluster/cloud/mpi_job.sh.template
paddlerec/core/engine/cluster/k8s/__init__.py
paddlerec/core/engine/cluster/k8s/cluster.sh
paddlerec/core/engine/cluster/k8s/k8s.yaml.template
paddlerec/core/engine/cluster/k8s/set_k8s_env.sh
paddlerec/core/metrics/__init__.py
paddlerec/core/metrics/auc.py
paddlerec/core/metrics/pairwise_pn.py
paddlerec/core/metrics/precision_recall.py
paddlerec/core/metrics/recall_k.py
paddlerec/core/modules/__init__.py
paddlerec/core/modules/coding/__init__.py
paddlerec/core/modules/coding/layers.py
paddlerec/core/modules/modul/__init__.py
paddlerec/core/modules/modul/build.py
paddlerec/core/modules/modul/layers.py
paddlerec/core/trainers/__init__.py
paddlerec/core/trainers/finetuning_trainer.py
paddlerec/core/trainers/general_trainer.py
paddlerec/core/trainers/framework/__init__.py
paddlerec/core/trainers/framework/dataset.py
paddlerec/core/trainers/framework/instance.py
paddlerec/core/trainers/framework/network.py
paddle_rec-1.8.5.1.dist-info/LICENSE
paddle_rec-1.8.5.1.dist-info/METADATA
paddle_rec-1.8.5.1.dist-info/WHEEL
paddle_rec-1.8.5.1.dist-info/top_level.txt
paddle_rec-1.8.5.1.dist-info/RECORD
