Metadata-Version: 2.1
Name: paddle-rec
Version: 1.8.5.1
Summary: paddle-rec
Home-page: https://github.com/PaddlePaddle/PaddleRec
Author: paddle-dev
Author-email: paddle-dev@baidu.com
License: UNKNOWN
Platform: UNKNOWN
Requires-Python: >=2.7
Requires-Dist: paddlepaddle (==1.8.5)
Requires-Dist: PyYAML (>=5.1.1)
